czyrym/__init__.py
czyrym/czyrym.py
czyrym-1.0.3.dist-info/METADATA
czyrym-1.0.3.dist-info/WHEEL
czyrym-1.0.3.dist-info/licenses/LICENSE
czyrym-1.0.3.dist-info/RECORD
