Metadata-Version: 2.4
Name: czyrym
Version: 1.0.3
Summary: Python library to decide if two polish words rhyme
Project-URL: Homepage, https://czterycztery.pl/programy/czyrym/
Author-email: Cztery Cztery <sdplbeqq@jadamspam.pl>
License-File: LICENSE
Requires-Python: >=3.8
Requires-Dist: pyphen>=0.14.0
